certbot_openshift/__init__.py
certbot_openshift/installer.py
certbot_openshift/tests/__init__.py
certbot_openshift/tests/test_installer.py
certbot_openshift-0.2.0.dist-info/DESCRIPTION.rst
certbot_openshift-0.2.0.dist-info/METADATA
certbot_openshift-0.2.0.dist-info/RECORD
certbot_openshift-0.2.0.dist-info/WHEEL
certbot_openshift-0.2.0.dist-info/entry_points.txt
certbot_openshift-0.2.0.dist-info/metadata.json
certbot_openshift-0.2.0.dist-info/top_level.txt
